somador3000/__init__.py
somador3000/__main__.py
somador3000/cli.py
somador3000/functions.py
somador3000-0.1.5.dist-info/LICENSE
somador3000-0.1.5.dist-info/METADATA
somador3000-0.1.5.dist-info/WHEEL
somador3000-0.1.5.dist-info/entry_points.txt
somador3000-0.1.5.dist-info/RECORD
