Metadata-Version: 2.3
Name: somador3000
Version: 0.1.5
Summary: Soma 3000 ao número passado como argumento
Author: Gustavo Rizzo S M de Albuquerque
Author-email: grizzo.albu@gmail.com
Requires-Python: >=3.13,<4.0
Classifier: Programming Language :: Python :: 3
Classifier: Programming Language :: Python :: 3.13
Requires-Dist: click (>=8.2.1,<9.0.0)
